shapez2/__init__.py
shapez2/blueprints.py
shapez2/blueprintsExtraData.py
shapez2/buildings.py
shapez2/gameObjects.py
shapez2/ingameData.py
shapez2/islands.py
shapez2/research.py
shapez2/shapeCodes.py
shapez2/shapeOperations.py
shapez2/shapeViewer.py
shapez2/translations.py
shapez2/utils.py
shapez2/versions.py
shapez2/gameCode/ConsistentRandom.py
shapez2/gameCode/MapShapeGenerator.py
shapez2/gameCode/RandomResearchShapeGenerator.py
shapez2/gameCode/__init__.py
shapez2/gameCode/otherClasses.py
shapez2/gameFiles/additionalBuildings.json
shapez2/gameFiles/buildings.json
shapez2/gameFiles/default-scenario.json
shapez2/gameFiles/hard-scenario.json
shapez2/gameFiles/hexagonal-scenario.json
shapez2/gameFiles/icons.json
shapez2/gameFiles/insane-scenario.json
shapez2/gameFiles/islands.json
shapez2/gameFiles/onboarding-scenario.json
shapez2/gameFiles/translations-en-US.json
shapez2/pygamePIL/__init__.py
shapez2/pygamePIL/draw.py
shapez2/pygamePIL/font.py
shapez2/pygamePIL/image.py
shapez2/pygamePIL/mask.py
shapez2/pygamePIL/transform.py
shapez2-2.1.1.dist-info/licenses/LICENSE
shapez2-2.1.1.dist-info/METADATA
shapez2-2.1.1.dist-info/WHEEL
shapez2-2.1.1.dist-info/top_level.txt
shapez2-2.1.1.dist-info/RECORD
