Metadata-Version: 2.4
Name: shapez2
Version: 2.1.1
Summary: A package to code tools for shapez 2
Author: Loupau 38
License-Expression: MIT
Project-URL: Homepage, https://github.com/Loupau38/shapez2-python
Project-URL: Documentation, https://loupau38.github.io/shapez2-python/
Classifier: Programming Language :: Python :: 3
Classifier: Operating System :: OS Independent
Requires-Python: >=3.13
License-File: LICENSE
Requires-Dist: Pillow>=11.1.0
Requires-Dist: fixedint>=0.2.0
Provides-Extra: pygame
Requires-Dist: pygame>=2.6.1; extra == "pygame"
Dynamic: license-file
